Metadata-Version: 1.1
Name: krithicprimefinder
Version: 0.0.1
Summary: To check prime number and do stuffs in prime
Home-page: UNKNOWN
Author: Krithic Sugumar
Author-email: krithic2001@gmail.com
License: MIT
Keywords: prime
Platform: UNKNOWN
Classifier: Development Status :: 5 - Production/Stable
Classifier: Intended Audience :: Education
Classifier: Operating System :: Microsoft :: Windows :: Windows 10
Classifier: License :: OSI Approved :: MIT License
Classifier: Programming Language :: Python :: 3
